pymobiledevice/__init__.py
pymobiledevice/afc.py
pymobiledevice/apps.py
pymobiledevice/ca.py
pymobiledevice/diagnostics_relay.py
pymobiledevice/file_relay.py
pymobiledevice/house_arrest.py
pymobiledevice/installation_proxy.py
pymobiledevice/lockdown.py
pymobiledevice/mobile_config.py
pymobiledevice/mobilebackup.py
pymobiledevice/mobilebackup2.py
pymobiledevice/notification_proxy.py
pymobiledevice/pcapd.py
pymobiledevice/plist_service.py
pymobiledevice/screenshotr.py
pymobiledevice/syslog.py
pymobiledevice/version.py
pymobiledevice/usbmux/__init__.py
pymobiledevice/usbmux/tcprelay.py
pymobiledevice/usbmux/usbmux.py
pymobiledevice/util/__init__.py
pymobiledevice/util/asciitables.py
pymobiledevice/util/bdev.py
pymobiledevice/util/bpatch.py
pymobiledevice/util/bplist.py
pymobiledevice/util/ccl_bplist.py
pymobiledevice/util/cert.py
pymobiledevice/util/cpio.py
pymobiledevice/util/lzss.py
pymobiledevice_qta-1.1.9.data/data/requirements.txt
pymobiledevice_qta-1.1.9.data/data/version.txt
test/__init__.py
test/afc_test.py
test/crashreportcopymobile_test.py
test/diagnostics_relay_test.py
test/house_arrest_test.py
test/installation_proxy_test.py
test/listdevice_test.py
test/screenshotr_test.py
test/syslog_relay_test.py
pymobiledevice_qta-1.1.9.dist-info/LICENSE.txt
pymobiledevice_qta-1.1.9.dist-info/METADATA
pymobiledevice_qta-1.1.9.dist-info/WHEEL
pymobiledevice_qta-1.1.9.dist-info/top_level.txt
pymobiledevice_qta-1.1.9.dist-info/RECORD
