Metadata-Version: 2.1
Name: pymobiledevice-qta
Version: 1.1.9
Summary: python implementation for libimobiledevice library
Home-page: https://github.com/qtacore/pymobiledevice
Author: QTA
License: Copyright(c)2010-2018 Tencent All Rights Reserved. 
Project-URL: pymobiledevice-qta Documentation, https://github.com/qtacore/pymobiledevice
Platform: UNKNOWN
Classifier: Programming Language :: Python :: 2.7
Classifier: Programming Language :: Python :: 3.6
Classifier: Programming Language :: Python :: 3.7
License-File: LICENSE.txt
Requires-Dist: construct (>=2.9.29)
Requires-Dist: pyasn1
Requires-Dist: future
Requires-Dist: six
Requires-Dist: biplist
Requires-Dist: M2Crypto (==0.32.0) ; sys_platform == "darwin"
